rh_1099/__init__.py
rh_1099/__main__.py
rh_1099/__version__.py
rh_1099/main.py
rh_1099/pdf_contents.py
rh_1099/pdf_parser/__init__.py
rh_1099/pdf_parser/parser_2020.py
rh_1099/pdf_parser/parser_interface.py
rh_1099/sales_transactions/__init__.py
rh_1099/sales_transactions/sales_2020.py
rh_1099/sales_transactions/sales_interface.py
rh_1099-1.0.1.dist-info/LICENSE
rh_1099-1.0.1.dist-info/METADATA
rh_1099-1.0.1.dist-info/WHEEL
rh_1099-1.0.1.dist-info/entry_points.txt
rh_1099-1.0.1.dist-info/top_level.txt
rh_1099-1.0.1.dist-info/RECORD
