Metadata-Version: 2.1
Name: rh-1099
Version: 1.0.1
Summary: Parses Robinhood 1099 tax document from PDF into CSV format
Home-page: https://github.com/kevinpark1217/Robinhood-1099-Parser
Author: Keun Tae (Kevin) Park
Author-email: kevin.park1217@gmail.com
License: UNKNOWN
Project-URL: Bug Reports, https://github.com/kevinpark1217/Robinhood-1099-Parser/issues
Project-URL: Funding, https://www.paypal.com/donate?business=P3M77TR7L8LBA&item_name=Thanks+for+supporting+my+work%21&currency_code=USD
Project-URL: Source, https://github.com/kevinpark1217/Robinhood-1099-Parser
Keywords: pdf,csv,parsing,excel,spreadsheet,tax,robinhood,1099
Platform: UNKNOWN
Classifier: Development Status :: 4 - Beta
Classifier: Intended Audience :: End Users/Desktop
Classifier: Intended Audience :: Financial and Insurance Industry
Classifier: Topic :: Office/Business :: Financial
Classifier: Topic :: Office/Business :: Financial :: Accounting
Classifier: Topic :: Office/Business :: Financial :: Investment
Classifier: Topic :: Office/Business :: Financial :: Spreadsheet
Classifier: Operating System :: POSIX :: Linux
Classifier: Operating System :: MacOS :: MacOS X
Classifier: Operating System :: Microsoft :: Windows :: Windows 10
Classifier: License :: OSI Approved :: GNU Affero General Public License v3
Classifier: Programming Language :: Python :: 3
Classifier: Programming Language :: Python :: 3.8
Classifier: Programming Language :: Python :: 3.9
Classifier: Programming Language :: Python :: 3 :: Only
Requires-Python: >=3.8, <4
Requires-Dist: pdfreader (>=0.1.9)
Requires-Dist: tqdm (>=4.59.0)
